setup.cfg
setup.py
pyxmlescpos.egg-info/PKG-INFO
pyxmlescpos.egg-info/SOURCES.txt
pyxmlescpos.egg-info/dependency_links.txt
pyxmlescpos.egg-info/requires.txt
pyxmlescpos.egg-info/top_level.txt
xmlescpos/__init__.py
xmlescpos/constants.py
xmlescpos/escpos.py
xmlescpos/exceptions.py
xmlescpos/printer.py
xmlescpos/supported_devices.py