Metadata-Version: 1.1
Name: pyxmlescpos
Version: 0.1.0
Summary: Print XML-defined Receipts on ESC/POS Receipt Printers
Home-page: https://github.com/fvdsn/py-xml-escpos
Author: Frédéric van der Essen & Manuel F Martinez
Author-email: fvdessen+x@gmail.com
License: MIT
Download-URL: https://github.com/fvdsn/py-xml-escpos/tarball/0.1.0
Keywords: printing receipt xml escpos
Platform: UNKNOWN
Classifier: Development Status :: 3 - Alpha
Classifier: Intended Audience :: Developers
Classifier: Topic :: Printing
Classifier: License :: OSI Approved :: MIT License
Classifier: Programming Language :: Python :: 2
Classifier: Programming Language :: Python :: 2.6
Classifier: Programming Language :: Python :: 2.7
